comfyconf/__init__.py
comfyconf/config.py
comfyconf/readers.py
comfyconf/utils.py
comfyconf/validators.py
comfyconf/tests/test_config.py
comfyconf/tests/test_readers.py
comfyconf/tests/test_utils.py
comfyconf/tests/test_validators.py
comfyconf-0.0.2.dist-info/LICENSE
comfyconf-0.0.2.dist-info/METADATA
comfyconf-0.0.2.dist-info/WHEEL
comfyconf-0.0.2.dist-info/top_level.txt
comfyconf-0.0.2.dist-info/RECORD
