Metadata-Version: 2.1
Name: comfyconf
Version: 0.0.2
Summary: YAML config parser
License: MIT License
Project-URL: Homepage, https://github.com/edager/comfyconf
Project-URL: Issues, https://github.com/edager/comfyconf/issues
Classifier: Operating System :: OS Independent
Classifier: Intended Audience :: Developers
Classifier: Development Status :: 3 - Alpha
Classifier: License :: OSI Approved :: MIT License
Classifier: Programming Language :: Python :: 3
Classifier: Programming Language :: Python :: 3.10
Requires-Python: >=3.10
License-File: LICENSE
Requires-Dist: pyyaml
Requires-Dist: jsonschema
Provides-Extra: dev
Requires-Dist: ruamel.yaml ; extra == 'dev'
Requires-Dist: yamale ; extra == 'dev'
Requires-Dist: pytest ; extra == 'dev'
Requires-Dist: coverage ; extra == 'dev'
Requires-Dist: black ; extra == 'dev'
Requires-Dist: isort ; extra == 'dev'
